flask_jwt_oidc/__init__.py
flask_jwt_oidc/exceptions.py
flask_jwt_oidc/jwt_manager.py
flask_jwt_oidc-0.7.0.dist-info/LICENSE
flask_jwt_oidc-0.7.0.dist-info/METADATA
flask_jwt_oidc-0.7.0.dist-info/WHEEL
flask_jwt_oidc-0.7.0.dist-info/RECORD
