Metadata-Version: 2.1
Name: flask-jwt-oidc
Version: 0.7.0
Summary: Opinionated flask oidc client
License: BSD 3-Clause
Author: thor wolpert
Author-email: thor@wolpert.ca
Requires-Python: >=3.9,<4.0
Classifier: License :: Other/Proprietary License
Classifier: Programming Language :: Python :: 3
Classifier: Programming Language :: Python :: 3.9
Classifier: Programming Language :: Python :: 3.10
Classifier: Programming Language :: Python :: 3.11
Classifier: Programming Language :: Python :: 3.12
Requires-Dist: Flask (>=2)
Requires-Dist: cachelib (>=0.13.0,<0.14.0)
Requires-Dist: python-jose (>=3.3.0,<4.0.0)
Requires-Dist: six (>=1.16.0,<2.0.0)
